mykurve/__init__.py
mykurve/const.py
mykurve/data_classes.py
mykurve/exceptions.py
mykurve/mykurve_api.py
mykurve/py.typed
mykurve-0.0.4.dist-info/LICENSE
mykurve-0.0.4.dist-info/METADATA
mykurve-0.0.4.dist-info/WHEEL
mykurve-0.0.4.dist-info/RECORD
