Metadata-Version: 2.1
Name: mykurve
Version: 0.0.4
Summary: Unofficial library to retrieve details of mykurve.com account
Home-page: https://ddb0515.github.io/mykurve
License: Apache-2.0
Author: Dario Budimir
Author-email: dario.budimir@gmail.com
Maintainer: Dario Budimir
Maintainer-email: dario.budimir@gmail.com
Requires-Python: >=3.10,<4.0
Classifier: License :: OSI Approved :: Apache Software License
Classifier: Programming Language :: Python :: 3
Classifier: Programming Language :: Python :: 3.10
Classifier: Programming Language :: Python :: 3.11
Classifier: Programming Language :: Python :: 3.12
Classifier: Programming Language :: Python :: 3.13
Requires-Dist: attr (>=0.3.2,<0.4.0)
Project-URL: Documentation, https://github.com/ddB0515/mykurve
Project-URL: Repository, https://github.com/ddB0515/mykurve
